gimel/VERSION
gimel/__init__.py
gimel/aws_api.py
gimel/cli.py
gimel/config.json.template
gimel/config.py
gimel/deploy.py
gimel/gimel.py
gimel/logger.py
gimel/vendor/redis/__init__.py
gimel/vendor/redis/__init__.pyc
gimel/vendor/redis/_compat.py
gimel/vendor/redis/_compat.pyc
gimel/vendor/redis/client.py
gimel/vendor/redis/client.pyc
gimel/vendor/redis/connection.py
gimel/vendor/redis/connection.pyc
gimel/vendor/redis/exceptions.py
gimel/vendor/redis/exceptions.pyc
gimel/vendor/redis/lock.py
gimel/vendor/redis/lock.pyc
gimel/vendor/redis/sentinel.py
gimel/vendor/redis/utils.py
gimel/vendor/redis/utils.pyc
gimel/vendor/redis/__pycache__/__init__.cpython-37.pyc
gimel/vendor/redis/__pycache__/_compat.cpython-37.pyc
gimel/vendor/redis/__pycache__/client.cpython-37.pyc
gimel/vendor/redis/__pycache__/connection.cpython-37.pyc
gimel/vendor/redis/__pycache__/exceptions.cpython-37.pyc
gimel/vendor/redis/__pycache__/lock.cpython-37.pyc
gimel/vendor/redis/__pycache__/utils.cpython-37.pyc
gimel-1.5.0.dist-info/LICENSE
gimel-1.5.0.dist-info/METADATA
gimel-1.5.0.dist-info/WHEEL
gimel-1.5.0.dist-info/entry_points.txt
gimel-1.5.0.dist-info/top_level.txt
gimel/vendor/redis-2.10.5.dist-info/DESCRIPTION.rst
gimel/vendor/redis-2.10.5.dist-info/METADATA
gimel/vendor/redis-2.10.5.dist-info/RECORD
gimel/vendor/redis-2.10.5.dist-info/WHEEL
gimel/vendor/redis-2.10.5.dist-info/metadata.json
gimel/vendor/redis-2.10.5.dist-info/top_level.txt
gimel-1.5.0.dist-info/RECORD
